LICENSE
MANIFEST.in
README.rst
setup.cfg
setup.py
stacked/__init__.py
stacked/stacked.py
stacked/test_stacked.py
stacked.egg-info/PKG-INFO
stacked.egg-info/SOURCES.txt
stacked.egg-info/dependency_links.txt
stacked.egg-info/top_level.txt