Metadata-Version: 1.0
Name: stacked
Version: 0.1.3
Summary: Stacking utilities
Home-page: https://github.com/0compute/stacked
Author: Arthur Noel
Author-email: arthur@0compute.net
License: GPL
Keywords: context stack
Platform: UNKNOWN
